nonebot_plugin_valve_server_query/__init__.py
nonebot_plugin_valve_server_query/__main__.py
nonebot_plugin_valve_server_query/authority.py
nonebot_plugin_valve_server_query/check.py
nonebot_plugin_valve_server_query/config.py
nonebot_plugin_valve_server_query/database.py
nonebot_plugin_valve_server_query/file.py
nonebot_plugin_valve_server_query/image.py
nonebot_plugin_valve_server_query/model.py
nonebot_plugin_valve_server_query/queries.py
nonebot_plugin_valve_server_query/static/fonts/f300W.ttf
nonebot_plugin_valve_server_query/static/fonts/f400W.ttf
nonebot_plugin_valve_server_query/static/fonts/f500W.ttf
nonebot_plugin_valve_server_query/static/fonts/f700W.ttf
nonebot_plugin_valve_server_query/static/icons/linux.svg
nonebot_plugin_valve_server_query/static/icons/macos.svg
nonebot_plugin_valve_server_query/static/icons/windows.svg
nonebot_plugin_valve_server_query/static/images/background.jpg
nonebot_plugin_valve_server_query/static/templates/group_info.css
nonebot_plugin_valve_server_query/static/templates/group_info.html
nonebot_plugin_valve_server_query/static/templates/server_info.css
nonebot_plugin_valve_server_query/static/templates/server_info.html
nonebot_plugin_valve_server_query/utils.py
nonebot_plugin_valve_server_query-0.5.8.dist-info/METADATA
nonebot_plugin_valve_server_query-0.5.8.dist-info/WHEEL
nonebot_plugin_valve_server_query-0.5.8.dist-info/RECORD
