Metadata-Version: 2.3
Name: nonebot-plugin-valve-server-query
Version: 0.5.8
Summary: nonebot-plugin-valve-server-query
Home-page: https://github.com/LiLuo-B/nonebot-plugin-valve-server-query
License: GPLv3
Author: LiLuo-B
Requires-Python: >=3.8, <4.0
Classifier: License :: Other/Proprietary License
Classifier: Programming Language :: Python :: 3
Classifier: Programming Language :: Python :: 3.8
Classifier: Programming Language :: Python :: 3.9
Classifier: Programming Language :: Python :: 3.10
Classifier: Programming Language :: Python :: 3.11
Classifier: Programming Language :: Python :: 3.12
Classifier: Programming Language :: Python :: 3.13
Requires-Dist: aiohttp (>=3.9.5)
Requires-Dist: jinja2 (>=3.1.4)
Requires-Dist: nonebot-adapter-onebot (>=2.2.3)
Requires-Dist: nonebot-plugin-htmlrender (>=0.3.1)
Requires-Dist: nonebot2 (>=2.2.0)
Requires-Dist: python-a2s (>=1.3.0)
Project-URL: Documentation, https://github.com/LiLuo-B/nonebot-plugin-valve-server-query/blob/main/README.md
Project-URL: Repository, https://github.com/LiLuo-B/nonebot-plugin-valve-server-query
